[
  {
    "Name": "BLK 1 LOT 01",
    "Close-to": "Lake",
    "Subdivision": "Section 1",
    "Lot Status": "Sold",
    "List Price": null,
    "Size [sqft]": null,
    "Street Address": null,
    "Listing Agent": null,
    "Listing Agent Phone Number": null,
    "Listing Link": null,
    "Location": "26.04998, -97.55175"
  },
  {
    "Name": "BLK 1 LOT 02",
    "Close-to": "Lake",
    "Subdivision": "Section 1",
    "Lot Status": "Sold",
    "List Price": null,
    "Size [sqft]": null,
    "Street Address": null,
    "Listing Agent": null,
    "Listing Agent Phone Number": null,
    "Listing Link": null,
    "Location": "26.05021, -97.55231"
  },
  {
    "Name": "BLK 1 LOT 03",
    "Close-to": "Lake",
    "Subdivision": "Section 1",
    "Lot Status": "Sold",
    "List Price": null,
    "Size [sqft]": null,
    "Street Address": null,
    "Listing Agent": null,
    "Listing Agent Phone Number": null,
    "Listing Link": null,
    "Location": "26.05060, -97.55275"
  },
  {
    "Name": "BLK 1 LOT 04",
    "Close-to": "Lake",
    "Subdivision": "Section 1",
    "Lot Status": "Sold",
    "List Price": null,
    "Size [sqft]": null,
    "Street Address": null,
    "Listing Agent": null,
    "Listing Agent Phone Number": null,
    "Listing Link": null,
    "Location": "26.05081, -97.55261"
  },
  {
    "Name": "BLK 1 LOT 05",
    "Close-to": "Lake",
    "Subdivision": "Section 1",
    "Lot Status": "Sold",
    "List Price": null,
    "Size [sqft]": null,
    "Street Address": null,
    "Listing Agent": null,
    "Listing Agent Phone Number": null,
    "Listing Link": null,
    "Location": "26.05105, -97.55255"
  },
  {
    "Name": "BLK 1 LOT 06",
    "Close-to": "Lake",
    "Subdivision": "Section 1",
    "Lot Status": "Sold",
    "List Price": null,
    "Size [sqft]": null,
    "Street Address": null,
    "Listing Agent": null,
    "Listing Agent Phone Number": null,
    "Listing Link": null,
    "Location": "26.05130, -97.55249"
  },
  {
    "Name": "BLK 1 LOT 07",
    "Close-to": "Lake",
    "Subdivision": "Section 1",
    "Lot Status": "Sold",
    "List Price": null,
    "Size [sqft]": null,
    "Street Address": null,
    "Listing Agent": null,
    "Listing Agent Phone Number": null,
    "Listing Link": null,
    "Location": "26.05156, -97.55245"
  },
  {
    "Name": "BLK 1 LOT 08",
    "Close-to": "Lake",
    "Subdivision": "Section 2",
    "Lot Status": "Listed",
    "List Price": 175000.0,
    "Size [sqft]": 16142.0,
    "Street Address": "1332 Giuseppe Verdi Ave",
    "Listing Agent": "Ralph Burks",
    "Listing Agent Phone Number": 19567786702.0,
    "Listing Link": null,
    "Location": "26.0518, -97.5524"
  },
  {
    "Name": "BLK 1 LOT 09",
    "Close-to": "Lake",
    "Subdivision": "Section 2",
    "Lot Status": "Under Contract",
    "List Price": 175000.0,
    "Size [sqft]": 14103.0,
    "Street Address": "1336 Giuseppe Verdi Ave",
    "Listing Agent": null,
    "Listing Agent Phone Number": null,
    "Listing Link": null,
    "Location": "26.05206, -97.55236"
  },
  {
    "Name": "BLK 1 LOT 10",
    "Close-to": "Lake",
    "Subdivision": "Section 2",
    "Lot Status": "Listed",
    "List Price": 165000.0,
    "Size [sqft]": 13855.0,
    "Street Address": "1340 Giuseppe Verdi Ave",
    "Listing Agent": "Patricia Perez",
    "Listing Agent Phone Number": null,
    "Listing Link": null,
    "Location": "26.0524, -97.5523"
  },
  {
    "Name": "BLK 1 LOT 11",
    "Close-to": "Lake",
    "Subdivision": "Section 2",
    "Lot Status": "Listed",
    "List Price": 165000.0,
    "Size [sqft]": 13862.0,
    "Street Address": "1344 Giuseppe Verdi Ave",
    "Listing Agent": "Benjamin Devries",
    "Listing Agent Phone Number": null,
    "Listing Link": null,
    "Location": "26.0526, -97.5524"
  },
  {
    "Name": "BLK 1 LOT 12",
    "Close-to": "Lake",
    "Subdivision": "Section 2",
    "Lot Status": "Under Contract",
    "List Price": 175000.0,
    "Size [sqft]": 13719.0,
    "Street Address": "1348 Giuseppe Verdi Ave",
    "Listing Agent": null,
    "Listing Agent Phone Number": null,
    "Listing Link": null,
    "Location": "26.05294, -97.55240"
  },
  {
    "Name": "BLK 1 LOT 13",
    "Close-to": "Lake",
    "Subdivision": "Section 2",
    "Lot Status": "Available",
    "List Price": 165000.0,
    "Size [sqft]": 12747.0,
    "Street Address": "1352 Giuseppe Verdi Ave",
    "Listing Agent": "For Sale By Owner",
    "Listing Agent Phone Number": 19563055246.0,
    "Listing Link": null,
    "Location": "26.0532, -97.5523"
  },
  {
    "Name": "BLK 1 LOT 14",
    "Close-to": "Lake",
    "Subdivision": "Section 2",
    "Lot Status": "Available",
    "List Price": 175000.0,
    "Size [sqft]": 12496.0,
    "Street Address": "1356 Giuseppe Verdi Ave",
    "Listing Agent": "For Sale By Owner",
    "Listing Agent Phone Number": 19563055246.0,
    "Listing Link": null,
    "Location": "26.0535, -97.5523"
  },
  {
    "Name": "BLK 1 LOT 15",
    "Close-to": "Lake",
    "Subdivision": "Section 2",
    "Lot Status": "Reserved",
    "List Price": 225000.0,
    "Size [sqft]": 12888.0,
    "Street Address": "1367 Giuseppe Verdi Ave",
    "Listing Agent": null,
    "Listing Agent Phone Number": null,
    "Listing Link": null,
    "Location": "26.05374, -97.55241"
  },
  {
    "Name": "BLK 1 LOT 16",
    "Close-to": "Lake",
    "Subdivision": "Section 3",
    "Lot Status": "Future",
    "List Price": null,
    "Size [sqft]": null,
    "Street Address": null,
    "Listing Agent": null,
    "Listing Agent Phone Number": null,
    "Listing Link": null,
    "Location": "26.05404, -97.55242"
  },
  {
    "Name": "BLK 1 LOT 17",
    "Close-to": "Lake",
    "Subdivision": "Section 3",
    "Lot Status": "Future",
    "List Price": null,
    "Size [sqft]": null,
    "Street Address": null,
    "Listing Agent": null,
    "Listing Agent Phone Number": null,
    "Listing Link": null,
    "Location": "26.05431, -97.55249"
  },
  {
    "Name": "BLK 1 LOT 18",
    "Close-to": "Lake",
    "Subdivision": "Section 3",
    "Lot Status": "Future",
    "List Price": null,
    "Size [sqft]": null,
    "Street Address": null,
    "Listing Agent": null,
    "Listing Agent Phone Number": null,
    "Listing Link": null,
    "Location": "26.05458, -97.55256"
  },
  {
    "Name": "BLK 1 LOT 19",
    "Close-to": "Lake",
    "Subdivision": "Section 3",
    "Lot Status": "Future",
    "List Price": null,
    "Size [sqft]": null,
    "Street Address": null,
    "Listing Agent": null,
    "Listing Agent Phone Number": null,
    "Listing Link": null,
    "Location": "26.05485, -97.55262"
  },
  {
    "Name": "BLK 1 LOT 20",
    "Close-to": "Lake",
    "Subdivision": "Section 3",
    "Lot Status": "Future",
    "List Price": null,
    "Size [sqft]": null,
    "Street Address": null,
    "Listing Agent": null,
    "Listing Agent Phone Number": null,
    "Listing Link": null,
    "Location": "26.05504, -97.55281"
  },
  {
    "Name": "BLK 1 LOT 21",
    "Close-to": "Lake",
    "Subdivision": "Section 3",
    "Lot Status": "Future",
    "List Price": null,
    "Size [sqft]": null,
    "Street Address": null,
    "Listing Agent": null,
    "Listing Agent Phone Number": null,
    "Listing Link": null,
    "Location": "26.05490, -97.55304"
  },
  {
    "Name": "BLK 1 LOT 22",
    "Close-to": "Lake",
    "Subdivision": "Section 3",
    "Lot Status": "Future",
    "List Price": null,
    "Size [sqft]": null,
    "Street Address": null,
    "Listing Agent": null,
    "Listing Agent Phone Number": null,
    "Listing Link": null,
    "Location": "26.05453, -97.55307"
  },
  {
    "Name": "BLK 1 LOT 23",
    "Close-to": "Lake",
    "Subdivision": "Section 3",
    "Lot Status": "Future",
    "List Price": null,
    "Size [sqft]": null,
    "Street Address": null,
    "Listing Agent": null,
    "Listing Agent Phone Number": null,
    "Listing Link": null,
    "Location": "26.05426, -97.55301"
  },
  {
    "Name": "BLK 1 LOT 24",
    "Close-to": "Lake",
    "Subdivision": "Section 3",
    "Lot Status": "Future",
    "List Price": null,
    "Size [sqft]": null,
    "Street Address": null,
    "Listing Agent": null,
    "Listing Agent Phone Number": null,
    "Listing Link": null,
    "Location": "26.05389, -97.55291"
  },
  {
    "Name": "BLK 2 LOT 01",
    "Close-to": "School",
    "Subdivision": "Section 1",
    "Lot Status": "Sold",
    "List Price": null,
    "Size [sqft]": null,
    "Street Address": null,
    "Listing Agent": null,
    "Listing Agent Phone Number": null,
    "Listing Link": null,
    "Location": "26.05063, -97.55300"
  },
  {
    "Name": "BLK 2 LOT 02",
    "Close-to": "School",
    "Subdivision": "Section 1",
    "Lot Status": "Sold",
    "List Price": null,
    "Size [sqft]": null,
    "Street Address": null,
    "Listing Agent": null,
    "Listing Agent Phone Number": null,
    "Listing Link": null,
    "Location": "26.05095, -97.55303"
  },
  {
    "Name": "BLK 2 LOT 03",
    "Close-to": "School",
    "Subdivision": "Section 1",
    "Lot Status": "Sold",
    "List Price": null,
    "Size [sqft]": null,
    "Street Address": null,
    "Listing Agent": null,
    "Listing Agent Phone Number": null,
    "Listing Link": null,
    "Location": "26.05115, -97.55296"
  },
  {
    "Name": "BLK 2 LOT 04",
    "Close-to": "School",
    "Subdivision": "Section 1",
    "Lot Status": "Sold",
    "List Price": null,
    "Size [sqft]": null,
    "Street Address": null,
    "Listing Agent": null,
    "Listing Agent Phone Number": null,
    "Listing Link": null,
    "Location": "26.05135, -97.55292"
  },
  {
    "Name": "BLK 2 LOT 05",
    "Close-to": "School",
    "Subdivision": "Section 1",
    "Lot Status": "Sold",
    "List Price": null,
    "Size [sqft]": null,
    "Street Address": null,
    "Listing Agent": null,
    "Listing Agent Phone Number": null,
    "Listing Link": null,
    "Location": "26.05156, -97.55288"
  },
  {
    "Name": "BLK 2 LOT 06",
    "Close-to": "School",
    "Subdivision": "Section 2",
    "Lot Status": "Under Contract",
    "List Price": 90000.0,
    "Size [sqft]": 7135.0,
    "Street Address": "1331 Giuseppe Verdi Ave",
    "Listing Agent": null,
    "Listing Agent Phone Number": null,
    "Listing Link": null,
    "Location": "26.05177, -97.55282"
  },
  {
    "Name": "BLK 2 LOT 07",
    "Close-to": "School",
    "Subdivision": "Section 2",
    "Lot Status": "Under Contract",
    "List Price": 90000.0,
    "Size [sqft]": 6979.0,
    "Street Address": "1335 Giuseppe Verdi Ave",
    "Listing Agent": null,
    "Listing Agent Phone Number": null,
    "Listing Link": null,
    "Location": "26.05194, -97.55283"
  },
  {
    "Name": "BLK 2 LOT 08",
    "Close-to": "School",
    "Subdivision": "Section 2",
    "Lot Status": "Listed",
    "List Price": 75000.0,
    "Size [sqft]": 7610.0,
    "Street Address": "1339 Giuseppe Verdi Ave",
    "Listing Agent": "Ralph Burks",
    "Listing Agent Phone Number": 19567786702.0,
    "Listing Link": "Zillow Link - https://www.zillow.com/homedetails/1339-Giuseppe-Verdi-Ave-LOT-8-Olmito-TX-78575/451119647_zpid/",
    "Location": "26.0521, -97.5528"
  },
  {
    "Name": "BLK 2 LOT 09",
    "Close-to": "School",
    "Subdivision": "Section 2",
    "Lot Status": "Under Contract",
    "List Price": 90000.0,
    "Size [sqft]": 7590.0,
    "Street Address": "1343 Giuseppe Verdi Ave",
    "Listing Agent": null,
    "Listing Agent Phone Number": null,
    "Listing Link": null,
    "Location": "26.05232, -97.55288"
  },
  {
    "Name": "BLK 2 LOT 10",
    "Close-to": "School",
    "Subdivision": "Section 2",
    "Lot Status": "Under Contract",
    "List Price": 90000.0,
    "Size [sqft]": 8147.0,
    "Street Address": "1347 Giuseppe Verdi Ave",
    "Listing Agent": null,
    "Listing Agent Phone Number": null,
    "Listing Link": null,
    "Location": "26.05251, -97.55289"
  },
  {
    "Name": "BLK 2 LOT 11",
    "Close-to": "School",
    "Subdivision": "Section 2",
    "Lot Status": "Under Contract",
    "List Price": 90000.0,
    "Size [sqft]": 7941.0,
    "Street Address": "1351 Giuseppe Verdi Ave",
    "Listing Agent": null,
    "Listing Agent Phone Number": null,
    "Listing Link": null,
    "Location": "26.05272, -97.55289"
  },
  {
    "Name": "BLK 2 LOT 12",
    "Close-to": "School",
    "Subdivision": "Section 2",
    "Lot Status": "Under Contract",
    "List Price": 90000.0,
    "Size [sqft]": 7941.0,
    "Street Address": "1355 Giuseppe Verdi Ave",
    "Listing Agent": null,
    "Listing Agent Phone Number": null,
    "Listing Link": null,
    "Location": "26.05291, -97.55289"
  },
  {
    "Name": "BLK 2 LOT 13",
    "Close-to": "School",
    "Subdivision": "Section 2",
    "Lot Status": "Listed",
    "List Price": 90000.0,
    "Size [sqft]": 7941.0,
    "Street Address": "1359 Giuseppe Verdi Ave",
    "Listing Agent": "Ralph Burks",
    "Listing Agent Phone Number": 19567786702.0,
    "Listing Link": "Zillow Link - https://www.zillow.com/homedetails/1359-Giuseppe-Verdi-Ave-LOT-13-Olmito-TX-78575/451120072_zpid/",
    "Location": "26.0531, -97.5528"
  },
  {
    "Name": "BLK 2 LOT 14",
    "Close-to": "School",
    "Subdivision": "Section 2",
    "Lot Status": "Available",
    "List Price": 90000.0,
    "Size [sqft]": 7854.0,
    "Street Address": "1363 Giuseppe Verdi Ave",
    "Listing Agent": "For Sale By Owner",
    "Listing Agent Phone Number": 19563055246.0,
    "Listing Link": null,
    "Location": "26.0533, -97.5528"
  },
  {
    "Name": "BLK 2 LOT 15",
    "Close-to": "School",
    "Subdivision": "Section 2",
    "Lot Status": "Under Contract",
    "List Price": 90000.0,
    "Size [sqft]": 11151.0,
    "Street Address": "1360 Giuseppe Verdi Ave",
    "Listing Agent": null,
    "Listing Agent Phone Number": null,
    "Listing Link": null,
    "Location": "26.05362, -97.55281"
  },
  {
    "Name": "BLK 2 LOT 16",
    "Close-to": "School",
    "Subdivision": "Section 3",
    "Lot Status": "Future",
    "List Price": null,
    "Size [sqft]": null,
    "Street Address": null,
    "Listing Agent": null,
    "Listing Agent Phone Number": null,
    "Listing Link": null,
    "Location": "26.05355, -97.55308"
  },
  {
    "Name": "BLK 2 LOT 17",
    "Close-to": "School",
    "Subdivision": "Section 3",
    "Lot Status": "Future",
    "List Price": null,
    "Size [sqft]": null,
    "Street Address": null,
    "Listing Agent": null,
    "Listing Agent Phone Number": null,
    "Listing Link": null,
    "Location": "26.05370, -97.55327"
  },
  {
    "Name": "BLK 2 LOT 18",
    "Close-to": "Retention Pond",
    "Subdivision": "Section 3",
    "Lot Status": "Future",
    "List Price": null,
    "Size [sqft]": null,
    "Street Address": null,
    "Listing Agent": null,
    "Listing Agent Phone Number": null,
    "Listing Link": null,
    "Location": "26.05381, -97.55343"
  },
  {
    "Name": "BLK 2 LOT 19",
    "Close-to": "Retention Pond",
    "Subdivision": "Section 3",
    "Lot Status": "Future",
    "List Price": null,
    "Size [sqft]": null,
    "Street Address": null,
    "Listing Agent": null,
    "Listing Agent Phone Number": null,
    "Listing Link": null,
    "Location": "26.05393, -97.55363"
  },
  {
    "Name": "BLK 2 LOT 20",
    "Close-to": "Retention Pond",
    "Subdivision": "Section 3",
    "Lot Status": "Future",
    "List Price": null,
    "Size [sqft]": null,
    "Street Address": null,
    "Listing Agent": null,
    "Listing Agent Phone Number": null,
    "Listing Link": null,
    "Location": "26.05411, -97.55372"
  },
  {
    "Name": "BLK 2 LOT 21",
    "Close-to": "Retention Pond",
    "Subdivision": "Section 3",
    "Lot Status": "Future",
    "List Price": null,
    "Size [sqft]": null,
    "Street Address": null,
    "Listing Agent": null,
    "Listing Agent Phone Number": null,
    "Listing Link": null,
    "Location": "26.05428, -97.55380"
  },
  {
    "Name": "BLK 2 LOT 22",
    "Close-to": "Retention Pond",
    "Subdivision": "Section 3",
    "Lot Status": "Future",
    "List Price": null,
    "Size [sqft]": null,
    "Street Address": null,
    "Listing Agent": null,
    "Listing Agent Phone Number": null,
    "Listing Link": null,
    "Location": "26.05455, -97.55377"
  },
  {
    "Name": "BLK 2 LOT 23",
    "Close-to": "Retention Pond",
    "Subdivision": "Section 3",
    "Lot Status": "Future",
    "List Price": null,
    "Size [sqft]": null,
    "Street Address": null,
    "Listing Agent": null,
    "Listing Agent Phone Number": null,
    "Listing Link": null,
    "Location": "26.05466, -97.55383"
  },
  {
    "Name": "BLK 2 LOT 24",
    "Close-to": "Canal",
    "Subdivision": "Section 3",
    "Lot Status": "Future",
    "List Price": null,
    "Size [sqft]": null,
    "Street Address": null,
    "Listing Agent": null,
    "Listing Agent Phone Number": null,
    "Listing Link": null,
    "Location": "26.05480, -97.55378"
  },
  {
    "Name": "BLK 2 LOT 25",
    "Close-to": "Canal",
    "Subdivision": "Section 3",
    "Lot Status": "Future",
    "List Price": null,
    "Size [sqft]": null,
    "Street Address": null,
    "Listing Agent": null,
    "Listing Agent Phone Number": null,
    "Listing Link": null,
    "Location": "26.05487, -97.55366"
  },
  {
    "Name": "BLK 2 LOT 26",
    "Close-to": "Canal",
    "Subdivision": "Section 3",
    "Lot Status": "Future",
    "List Price": null,
    "Size [sqft]": null,
    "Street Address": null,
    "Listing Agent": null,
    "Listing Agent Phone Number": null,
    "Listing Link": null,
    "Location": "26.05511, -97.55351"
  },
  {
    "Name": "BLK 2 LOT 27",
    "Close-to": "Canal",
    "Subdivision": "Section 3",
    "Lot Status": "Future",
    "List Price": null,
    "Size [sqft]": null,
    "Street Address": null,
    "Listing Agent": null,
    "Listing Agent Phone Number": null,
    "Listing Link": null,
    "Location": "26.05522, -97.55334"
  },
  {
    "Name": "BLK 2 LOT 28",
    "Close-to": "Canal",
    "Subdivision": "Section 3",
    "Lot Status": "Future",
    "List Price": null,
    "Size [sqft]": null,
    "Street Address": null,
    "Listing Agent": null,
    "Listing Agent Phone Number": null,
    "Listing Link": null,
    "Location": "26.05533, -97.55316"
  },
  {
    "Name": "BLK 2 LOT 29",
    "Close-to": "Canal",
    "Subdivision": "Section 3",
    "Lot Status": "Future",
    "List Price": null,
    "Size [sqft]": null,
    "Street Address": null,
    "Listing Agent": null,
    "Listing Agent Phone Number": null,
    "Listing Link": null,
    "Location": "26.05544, -97.55298"
  }
]